CartiMorph_nnUNet/__init__.py
CartiMorph_nnUNet/configuration.py
CartiMorph_nnUNet/paths.py
CartiMorph_nnUNet/dataset_conversion/__init__.py
CartiMorph_nnUNet/dataset_conversion/utils.py
CartiMorph_nnUNet/evaluation/__init__.py
CartiMorph_nnUNet/evaluation/add_mean_dice_to_json.py
CartiMorph_nnUNet/evaluation/evaluator.py
CartiMorph_nnUNet/evaluation/metrics.py
CartiMorph_nnUNet/evaluation/model_selection/__init__.py
CartiMorph_nnUNet/evaluation/model_selection/ensemble.py
CartiMorph_nnUNet/evaluation/model_selection/figure_out_what_to_submit.py
CartiMorph_nnUNet/experiment_planning/DatasetAnalyzer.py
CartiMorph_nnUNet/experiment_planning/__init__.py
CartiMorph_nnUNet/experiment_planning/common_utils.py
CartiMorph_nnUNet/experiment_planning/experiment_planner_baseline_2DUNet.py
CartiMorph_nnUNet/experiment_planning/experiment_planner_baseline_2DUNet_v21.py
CartiMorph_nnUNet/experiment_planning/experiment_planner_baseline_3DUNet.py
CartiMorph_nnUNet/experiment_planning/experiment_planner_baseline_3DUNet_v21.py
CartiMorph_nnUNet/experiment_planning/nnUNet_plan_and_preprocess.py
CartiMorph_nnUNet/experiment_planning/summarize_plans.py
CartiMorph_nnUNet/experiment_planning/utils.py
CartiMorph_nnUNet/experiment_planning/alternative_experiment_planning/__init__.py
CartiMorph_nnUNet/experiment_planning/alternative_experiment_planning/experiment_planner_baseline_3DUNet_v21_11GB.py
CartiMorph_nnUNet/experiment_planning/alternative_experiment_planning/experiment_planner_baseline_3DUNet_v21_16GB.py
CartiMorph_nnUNet/experiment_planning/alternative_experiment_planning/experiment_planner_baseline_3DUNet_v21_32GB.py
CartiMorph_nnUNet/experiment_planning/alternative_experiment_planning/experiment_planner_baseline_3DUNet_v21_3convperstage.py
CartiMorph_nnUNet/experiment_planning/alternative_experiment_planning/experiment_planner_baseline_3DUNet_v22.py
CartiMorph_nnUNet/experiment_planning/alternative_experiment_planning/experiment_planner_baseline_3DUNet_v23.py
CartiMorph_nnUNet-1.7.15.dist-info/LICENSE
CartiMorph_nnUNet-1.7.15.dist-info/METADATA
CartiMorph_nnUNet-1.7.15.dist-info/WHEEL
CartiMorph_nnUNet-1.7.15.dist-info/entry_points.txt
CartiMorph_nnUNet-1.7.15.dist-info/top_level.txt
CartiMorph_nnUNet-1.7.15.dist-info/RECORD
