Metadata-Version: 2.1
Name: CartiMorph-nnUNet
Version: 1.7.15
Summary: nnU-Net with minor revisions tailored for the CartiMorph framework.
Home-page: https://github.com/YongchengYAO/CartiMorph-nnUNet
Author: Yongcheng Yao
License: Apache License Version 2.0, January 2004
Keywords: deep learning,image segmentation,medical image analysis,medical image segmentation,nnU-Net,nnunet
License-File: LICENSE
Requires-Dist: torch >1.10.0
Requires-Dist: tqdm
Requires-Dist: dicom2nifti
Requires-Dist: scikit-image >=0.14
Requires-Dist: medpy
Requires-Dist: scipy
Requires-Dist: batchgenerators >=0.23
Requires-Dist: numpy
Requires-Dist: scikit-learn
Requires-Dist: SimpleITK
Requires-Dist: pandas
Requires-Dist: requests
Requires-Dist: nibabel
Requires-Dist: tifffile
Requires-Dist: matplotlib
